APIX/__init__.py
APIX/chatinvx.py
Inchatvx-1.0.0.dist-info/METADATA
Inchatvx-1.0.0.dist-info/WHEEL
Inchatvx-1.0.0.dist-info/top_level.txt
Inchatvx-1.0.0.dist-info/RECORD
