Metadata-Version: 2.2
Name: Inchatvx
Version: 1.0.0
Summary: A Python library for interacting with the InChat API
Home-page: https://github.com/Vermouth4/
Author: Vermouth
Author-email: Vermouth@gmail.com
Classifier: Programming Language :: Python :: 3
Classifier: License :: OSI Approved :: MIT License
Classifier: Operating System :: OS Independent
Requires-Python: >=3.6
Requires-Dist: requests
Dynamic: author
Dynamic: author-email
Dynamic: classifier
Dynamic: description
Dynamic: description-content-type
Dynamic: home-page
Dynamic: requires-dist
Dynamic: requires-python
Dynamic: summary
